{
  "sections": {
    "main": {
      "type": "main-page",
      "disabled": true,
      "settings": {
        "padding_top": 36,
        "padding_bottom": 28
      }
    },
    "3a2417ac-352f-492f-aab0-b338ac316bef": {
      "type": "section-text",
      "settings": {
        "mt": 50,
        "show_border": false,
        "text": "Stores & Partners"
      }
    },
    "91ccfa83-7d90-4634-81c3-88d585e4bf22": {
      "type": "stores-form",
      "settings": {
        "text": "<p>Interested in carrying our products? Do you want to see our products sold in a store near you? Send us an email below and let us know where you’d like Yay for Earth<\/p>"
      }
    }
  },
  "order": [
    "main",
    "3a2417ac-352f-492f-aab0-b338ac316bef",
    "91ccfa83-7d90-4634-81c3-88d585e4bf22"
  ]
}
